dep_prune/__init__.py
dep_prune-0.1.0.dist-info/WHEEL
dep_prune-0.1.0.dist-info/entry_points.txt
dep_prune-0.1.0.dist-info/METADATA
dep_prune-0.1.0.dist-info/RECORD
