Metadata-Version: 2.3
Name: dep-prune
Version: 0.1.0
Summary: Add your description here
Author: Josh Cunningham
Author-email: Josh Cunningham <josh.cu@gmail.com>
Requires-Dist: toml>=0.10.2
Requires-Python: >=3.12
